hyper/__init__.py
hyper/error.py
hyper/license.py
hyper/mapper.py
hyper/requestor.py
hyper_python-0.0.1.dist-info/LICENSE
hyper_python-0.0.1.dist-info/METADATA
hyper_python-0.0.1.dist-info/WHEEL
hyper_python-0.0.1.dist-info/top_level.txt
hyper_python-0.0.1.dist-info/RECORD
