Metadata-Version: 2.1
Name: hyper-python
Version: 0.0.1
Summary: Python library for the Hyper API.
Home-page: https://github.com/meta-labs/hyper-python
Author: Hyper
Author-email: support@hyper.co
License: MIT
Project-URL: Documentation, https://docs.hyper.co/reference
Project-URL: Source Code, https://github.com/meta-labs/hyper-python
Platform: UNKNOWN
Classifier: Programming Language :: Python :: 3
Classifier: License :: OSI Approved :: MIT License
Classifier: Operating System :: OS Independent
Requires-Python: >=3.0
License-File: LICENSE
